osirix/__init__.py
osirix/browser_controller.py
osirix/build_doc.py
osirix/dcm_pix.py
osirix/dicom.py
osirix/exceptions.py
osirix/osirix_utils.py
osirix/response_processor.py
osirix/roi.py
osirix/test_package.py
osirix/viewer_controller.py
osirix/vr_controller.py
osirix/wait.py
osirix/examples/__init__.py
osirix/examples/example_template.py
pyosirix-0.2.1.dist-info/AUTHORS.rst
pyosirix-0.2.1.dist-info/LICENSE
pyosirix-0.2.1.dist-info/METADATA
pyosirix-0.2.1.dist-info/WHEEL
pyosirix-0.2.1.dist-info/top_level.txt
pyosirix-0.2.1.dist-info/RECORD
