Metadata-Version: 2.1
Name: pyosirix
Version: 0.2.1
Summary: Pythonic interface for interacting with Osirix through gRPC protocol
Home-page: https://github.com/osirixgrpc/pyosirix
Author: Timothy Sum Hon Mun, Matthew D Blackledge
Author-email: timothy22000@gmail.com, timothy.sumhonmun@icr.ac.uk, mattyblackledge@gmail.com, matthew.blackledge@icr.ac.uk
License: BSD license
Keywords: pyosirix
Classifier: Development Status :: 4 - Beta
Classifier: Intended Audience :: Developers
Classifier: Intended Audience :: Education
Classifier: Intended Audience :: Science/Research
Classifier: License :: OSI Approved :: BSD License
Classifier: Natural Language :: English
Classifier: Topic :: Scientific/Engineering
Classifier: Topic :: Scientific/Engineering :: Mathematics
Classifier: Topic :: Scientific/Engineering :: Artificial Intelligence
Classifier: Topic :: Software Development
Classifier: Topic :: Software Development :: Libraries
Classifier: Topic :: Software Development :: Libraries :: Python Modules
Classifier: Programming Language :: Python :: 3
Classifier: Programming Language :: Python :: 3.6
Classifier: Programming Language :: Python :: 3.7
Classifier: Programming Language :: Python :: 3.8
Requires-Python: >=3.6
License-File: LICENSE
License-File: AUTHORS.rst
Requires-Dist: google-cloud-core (==1.7.1)
Requires-Dist: matplotlib (>=3.4.2)
Requires-Dist: numpy (>=1.19.5)
Requires-Dist: pdoc (==8.0.0)
Requires-Dist: pydicom (==2.2.0)
Requires-Dist: pytest (==6.2.4)
Requires-Dist: setuptools (==47.1.0)
Requires-Dist: tqdm (==4.49.0)
Requires-Dist: pip (>=19.2.3)
Requires-Dist: bump2version (==0.5.11)
Requires-Dist: wheel (==0.33.6)
Requires-Dist: watchdog (==0.9.0)
Requires-Dist: flake8 (==3.7.8)
Requires-Dist: coverage (==4.5.4)
Requires-Dist: twine (==1.14.0)
Requires-Dist: build (==0.7.0)
Requires-Dist: osirixgrpc (>=0.2.1.dev0)
Requires-Dist: jupyter-book (==0.13.0)
Requires-Dist: pyppeteer (==1.0.2)
